claude_context_monitor/__init__.py
claude_context_monitor/cli.py
claude_context_monitor/handoff.py
claude_context_monitor/installer.py
claude_context_monitor/plan_detector.py
claude_context_monitor/realtime_monitor.py
claude_context_monitor/status.py
claude_context_monitor/token_animator.py
claude_context_monitor/turn_tracker.py
claude_context_monitor-1.4.2.dist-info/METADATA
claude_context_monitor-1.4.2.dist-info/WHEEL
claude_context_monitor-1.4.2.dist-info/entry_points.txt
claude_context_monitor-1.4.2.dist-info/licenses/LICENSE
claude_context_monitor-1.4.2.dist-info/RECORD
