Metadata-Version: 2.4
Name: claude-context-monitor
Version: 1.4.2
Summary: Advanced context monitoring and management for Claude Code
Project-URL: Repository, https://github.com/XiaoConstantine/claude-context-monitor
Project-URL: Issues, https://github.com/XiaoConstantine/claude-context-monitor/issues
Author-email: Xiao <constantine124@gmail.com>
License-File: LICENSE
Keywords: ai,claude,context,llm,monitoring
Classifier: Development Status :: 4 - Beta
Classifier: Intended Audience :: Developers
Classifier: Programming Language :: Python :: 3
Classifier: Programming Language :: Python :: 3.7
Classifier: Programming Language :: Python :: 3.8
Classifier: Programming Language :: Python :: 3.9
Classifier: Programming Language :: Python :: 3.10
Classifier: Programming Language :: Python :: 3.11
Classifier: Programming Language :: Python :: 3.12
Classifier: Topic :: Software Development :: Libraries :: Python Modules
Requires-Python: >=3.7
